[
	{
		"type": "input",
		"name": "firstName",
		"placeholder": "jonh",
		"label": "First Name",
		"value": "",
		"validations": [
				{
					"type": "required"
				},
				{
					"type":"minLength",
					"value": 5
				}	
			]	
	},
	{
		"type": "input",
		"name": "lastName",
		"placeholder": "Apples",
		"label": "Last Name",
		"value": "",
		"validations": [
			{
				"type": "required"
			},
			{
				"type":"minLength",
				"value": 5
			}	
		]
	},
	{
		"type": "email",
		"name": "email",
		"placeholder": "john@apples.com",
		"label": "Email",
		"value": "",
		"validations": [
			{
				"type": "required"
			},
			{
				"type":"email"
			}	
		]
	},
	{
		"type": "select",
		"name": "favoriteGame",
		"label": "Favorite Game",
		"value": "",
		"validations": [
			{
				"type": "required"
			}
		],
		"options": [
			{
				"id": 1,
				"label": "Halo"
			},
			{
				"id": 2,
				"label": "Fortnite"
			},
			{
				"id": 3,
				"label": "Minecraft"
			},
			{
				"id": 4,
				"label": "League of Legends"
			},
			{
				"id": 5,
				"label": "Counter Strike"
			},
			{
				"id": 6,
				"label": "Dota 2"
			}
		]
	}
]